unified_xai/__init__.py
unified_xai/config.py
unified_xai/core/__init__.py
unified_xai/core/analyzer.py
unified_xai/core/base.py
unified_xai/core/model_wrappers.py
unified_xai-0.1.1.dist-info/licenses/LICENSE
unified_xai-0.1.1.dist-info/METADATA
unified_xai-0.1.1.dist-info/WHEEL
unified_xai-0.1.1.dist-info/top_level.txt
unified_xai-0.1.1.dist-info/RECORD
