Metadata-Version: 2.4
Name: unified-xai
Version: 0.1.1
Summary: Unified XAI: An Explainable AI library for interpretable machine learning, Deep Learning and Artifical Intelligence.
Home-page: https://github.com/SatyamSingh8306/unified-xai
Author: Satyam Singh
Author-email: satyamsingh7734@gmail.com
License: MIT
Classifier: Development Status :: 3 - Alpha
Classifier: Intended Audience :: Developers
Classifier: Intended Audience :: Science/Research
Classifier: Topic :: Software Development :: Libraries
Classifier: Topic :: Scientific/Engineering :: Artificial Intelligence
Classifier: License :: OSI Approved :: MIT License
Classifier: Programming Language :: Python :: 3
Classifier: Programming Language :: Python :: 3.8
Classifier: Programming Language :: Python :: 3.9
Classifier: Programming Language :: Python :: 3.10
Requires-Python: >=3.8
License-File: LICENSE
Requires-Dist: numpy>=1.19.0
Requires-Dist: torch>=1.9.0
Requires-Dist: tensorflow>=2.6.0
Requires-Dist: scikit-learn>=0.24.0
Requires-Dist: matplotlib>=3.3.0
Requires-Dist: plotly>=5.0.0
Requires-Dist: lime>=0.2.0
Requires-Dist: shap>=0.40.0
Requires-Dist: opencv-python>=4.5.0
Requires-Dist: pandas>=1.3.0
Requires-Dist: pillow>=8.0.0
Requires-Dist: tqdm>=4.62.0
Provides-Extra: dev
Requires-Dist: pytest>=6.0; extra == "dev"
Requires-Dist: black; extra == "dev"
Requires-Dist: flake8; extra == "dev"
Requires-Dist: mypy; extra == "dev"
Provides-Extra: dashboard
Requires-Dist: streamlit>=1.0.0; extra == "dashboard"
Requires-Dist: dash>=2.0.0; extra == "dashboard"
Dynamic: author
Dynamic: author-email
Dynamic: classifier
Dynamic: description
Dynamic: description-content-type
Dynamic: home-page
Dynamic: license
Dynamic: license-file
Dynamic: provides-extra
Dynamic: requires-dist
Dynamic: requires-python
Dynamic: summary
